rochdi/__init__.py
rochdi/basher.py
rochdi/pipmake.py
rochdi/test.py
rochdi-0.0.2.dist-info/LICENSE
rochdi-0.0.2.dist-info/METADATA
rochdi-0.0.2.dist-info/WHEEL
rochdi-0.0.2.dist-info/top_level.txt
rochdi-0.0.2.dist-info/RECORD
